farscore-1.0.1.data/data/checkpoints/farscore_default.pth
farscore-1.0.1.data/data/data/test_dataset/TS1.csv
farscore-1.0.1.data/data/data/test_dataset/TS2.csv
farscore-1.0.1.data/data/data/test_dataset/TS3.csv
farscore-1.0.1.data/data/data/test_dataset/TSA.csv
farscore-1.0.1.data/data/data/test_dataset/TSB.csv
farscore-1.0.1.dist-info/licenses/LICENSE
model/__init__.py
model/cli.py
model/example.csv
model/farscore.py
model/farscore_finetune.py
model/farscore_pretrain.py
model/scripts/__init__.py
model/scripts/model/AttentiveFPGNN.py
model/scripts/model/__init__.py
model/scripts/model/utils.py
model/scripts/utils/__init__.py
model/scripts/utils/AttentiveFP/AttentiveLayers.py
model/scripts/utils/AttentiveFP/Featurizer.py
model/scripts/utils/AttentiveFP/__init__.py
model/scripts/utils/AttentiveFP/getFeatures.py
model/scripts/utils/mol/AttfpMPNN.py
model/scripts/utils/mol/__init__.py
model/scripts/utils/mol/assemble.py
model/scripts/utils/mol/basic.py
model/scripts/utils/mol/chemutils.py
model/scripts/utils/mol/cls.py
model/scripts/utils/mol/dataset.py
model/scripts/utils/mol/dfs.py
model/scripts/utils/mol/dgl_g.py
model/scripts/utils/mol/filter_valid_smiles.py
model/scripts/utils/mol/fingerprint.py
model/scripts/utils/mol/model.py
model/scripts/utils/mol/pyg.py
model/scripts/utils/nn/__init__.py
model/scripts/utils/nn/create.py
farscore-1.0.1.dist-info/METADATA
farscore-1.0.1.dist-info/WHEEL
farscore-1.0.1.dist-info/entry_points.txt
farscore-1.0.1.dist-info/top_level.txt
farscore-1.0.1.dist-info/RECORD
